phrasehunter/__init__.py
phrasehunter/__main__.py
phrasehunter/game.py
phrasehunter/phrase.py
phrase_hunter-0.1.1.dist-info/LICENSE
phrase_hunter-0.1.1.dist-info/METADATA
phrase_hunter-0.1.1.dist-info/WHEEL
phrase_hunter-0.1.1.dist-info/entry_points.txt
phrase_hunter-0.1.1.dist-info/top_level.txt
phrase_hunter-0.1.1.dist-info/RECORD
